[{"accession":"CX6B1_HUMAN","name":"CX6B1_HUMAN","interactions":[{"accession1":"CX6B1_HUMAN","accession2":"COX1_HUMAN","experiments":10},{"accession1":"CX6B1_HUMAN","accession2":"COX2_HUMAN","experiments":10},{"accession1":"CX6B1_HUMAN","accession2":"CX6A1_HUMAN","experiments":10},{"accession1":"CX6B1_HUMAN","accession2":"NDUA4_HUMAN","experiments":10},{"accession1":"CX6B1_HUMAN","accession2":"COX3_HUMAN","experiments":10}]},{"accession":"COX1_HUMAN","name":"COX1_HUMAN","interactions":[{"accession1":"COX1_HUMAN","accession2":"CX6B1_HUMAN","experiments":10},{"accession1":"COX1_HUMAN","accession2":"COX2_HUMAN","experiments":10},{"accession1":"COX1_HUMAN","accession2":"NDUA4_HUMAN","experiments":10}]},{"accession":"COX2_HUMAN","name":"COX2_HUMAN","interactions":[{"accession1":"COX2_HUMAN","accession2":"CX6B1_HUMAN","experiments":10},{"accession1":"COX2_HUMAN","accession2":"COX1_HUMAN","experiments":10},{"accession1":"COX2_HUMAN","accession2":"NDUA4_HUMAN","experiments":10},{"accession1":"COX2_HUMAN","accession2":"COX3_HUMAN","experiments":10}]},{"accession":"CX6A1_HUMAN","name":"CX6A1_HUMAN","interactions":[{"accession1":"CX6A1_HUMAN","accession2":"CX6B1_HUMAN","experiments":10},{"accession1":"CX6A1_HUMAN","accession2":"NDUA4_HUMAN","experiments":10}]},{"accession":"NDUA4_HUMAN","name":"NDUA4_HUMAN","interactions":[{"accession1":"NDUA4_HUMAN","accession2":"CX6B1_HUMAN","experiments":10},{"accession1":"NDUA4_HUMAN","accession2":"COX1_HUMAN","experiments":10},{"accession1":"NDUA4_HUMAN","accession2":"COX2_HUMAN","experiments":10},{"accession1":"NDUA4_HUMAN","accession2":"CX6A1_HUMAN","experiments":10},{"accession1":"NDUA4_HUMAN","accession2":"COX3_HUMAN","experiments":10}]},{"accession":"COX3_HUMAN","name":"COX3_HUMAN","interactions":[{"accession1":"COX3_HUMAN","accession2":"CX6B1_HUMAN","experiments":10},{"accession1":"COX3_HUMAN","accession2":"COX2_HUMAN","experiments":10},{"accession1":"COX3_HUMAN","accession2":"NDUA4_HUMAN","experiments":10}]}]