[{"accession":"GGA3_HUMAN","name":"GGA3_HUMAN","interactions":[{"accession1":"GGA3_HUMAN","accession2":"CLCA_HUMAN","experiments":1},{"accession1":"GGA3_HUMAN","accession2":"CLH1_HUMAN","experiments":1},{"accession1":"GGA3_HUMAN","accession2":"HGS_HUMAN","experiments":1},{"accession1":"GGA3_HUMAN","accession2":"ARF3_HUMAN","experiments":3},{"accession1":"GGA3_HUMAN","accession2":"CLCB_HUMAN","experiments":1},{"accession1":"GGA3_HUMAN","accession2":"VPS18_HUMAN","experiments":3},{"accession1":"GGA3_HUMAN","accession2":"ADA2A_HUMAN","experiments":1},{"accession1":"GGA3_HUMAN","accession2":"RAB4A_HUMAN","experiments":1},{"accession1":"GGA3_HUMAN","accession2":"CRK_HUMAN","experiments":2},{"accession1":"GGA3_HUMAN","accession2":"VPS11_HUMAN","experiments":1},{"accession1":"GGA3_HUMAN","accession2":"ITB1_HUMAN","experiments":2},{"accession1":"GGA3_HUMAN","accession2":"UBB_HUMAN","experiments":4},{"accession1":"GGA3_HUMAN","accession2":"TOLIP_HUMAN","experiments":1},{"accession1":"GGA3_HUMAN","accession2":"RAB5A_HUMAN","experiments":1},{"accession1":"GGA3_HUMAN","accession2":"ARF1_HUMAN","experiments":7},{"accession1":"GGA3_HUMAN","accession2":"RS27A_HUMAN","experiments":2},{"accession1":"GGA3_HUMAN","accession2":"ARF6_HUMAN","experiments":8},{"accession1":"GGA3_HUMAN","accession2":"GGA3_HUMAN","experiments":10},{"accession1":"GGA3_HUMAN","accession2":"CYH2_HUMAN","experiments":1},{"accession1":"GGA3_HUMAN","accession2":"RL40_HUMAN","experiments":2},{"accession1":"GGA3_HUMAN","accession2":"TS101_HUMAN","experiments":2},{"accession1":"GGA3_HUMAN","accession2":"RABE1_HUMAN","experiments":10},{"accession1":"GGA3_HUMAN","accession2":"UBC_HUMAN","experiments":10},{"accession1":"GGA3_HUMAN","accession2":"PACS1_HUMAN","experiments":9},{"accession1":"GGA3_HUMAN","accession2":"NEDD4_HUMAN","experiments":1}]},{"accession":"CLCA_HUMAN","name":"CLCA_HUMAN","interactions":[{"accession1":"CLCA_HUMAN","accession2":"GGA3_HUMAN","experiments":1},{"accession1":"CLCA_HUMAN","accession2":"CLH1_HUMAN","experiments":7},{"accession1":"CLCA_HUMAN","accession2":"HGS_HUMAN","experiments":1},{"accession1":"CLCA_HUMAN","accession2":"CLCB_HUMAN","experiments":4},{"accession1":"CLCA_HUMAN","accession2":"UBB_HUMAN","experiments":2},{"accession1":"CLCA_HUMAN","accession2":"RAB5A_HUMAN","experiments":1},{"accession1":"CLCA_HUMAN","accession2":"ARF1_HUMAN","experiments":1},{"accession1":"CLCA_HUMAN","accession2":"RS27A_HUMAN","experiments":2},{"accession1":"CLCA_HUMAN","accession2":"ARF6_HUMAN","experiments":1},{"accession1":"CLCA_HUMAN","accession2":"GGA3_HUMAN","experiments":1},{"accession1":"CLCA_HUMAN","accession2":"RL40_HUMAN","experiments":2},{"accession1":"CLCA_HUMAN","accession2":"RABE1_HUMAN","experiments":1},{"accession1":"CLCA_HUMAN","accession2":"UBC_HUMAN","experiments":3}]},{"accession":"CLH1_HUMAN","name":"CLH1_HUMAN","interactions":[{"accession1":"CLH1_HUMAN","accession2":"GGA3_HUMAN","experiments":1},{"accession1":"CLH1_HUMAN","accession2":"CLCA_HUMAN","experiments":7},{"accession1":"CLH1_HUMAN","accession2":"CLH1_HUMAN","experiments":10},{"accession1":"CLH1_HUMAN","accession2":"HGS_HUMAN","experiments":6},{"accession1":"CLH1_HUMAN","accession2":"CLCB_HUMAN","experiments":4},{"accession1":"CLH1_HUMAN","accession2":"ARF1_HUMAN","experiments":1},{"accession1":"CLH1_HUMAN","accession2":"ARF6_HUMAN","experiments":1},{"accession1":"CLH1_HUMAN","accession2":"GGA3_HUMAN","experiments":1},{"accession1":"CLH1_HUMAN","accession2":"UBC_HUMAN","experiments":1}]},{"accession":"HGS_HUMAN","name":"HGS_HUMAN","interactions":[{"accession1":"HGS_HUMAN","accession2":"GGA3_HUMAN","experiments":1},{"accession1":"HGS_HUMAN","accession2":"CLCA_HUMAN","experiments":1},{"accession1":"HGS_HUMAN","accession2":"CLH1_HUMAN","experiments":6},{"accession1":"HGS_HUMAN","accession2":"HGS_HUMAN","experiments":6},{"accession1":"HGS_HUMAN","accession2":"CLCB_HUMAN","experiments":1},{"accession1":"HGS_HUMAN","accession2":"RAB4A_HUMAN","experiments":1},{"accession1":"HGS_HUMAN","accession2":"UBB_HUMAN","experiments":2},{"accession1":"HGS_HUMAN","accession2":"RAB5A_HUMAN","experiments":1},{"accession1":"HGS_HUMAN","accession2":"RS27A_HUMAN","experiments":2},{"accession1":"HGS_HUMAN","accession2":"GGA3_HUMAN","experiments":1},{"accession1":"HGS_HUMAN","accession2":"RL40_HUMAN","experiments":2},{"accession1":"HGS_HUMAN","accession2":"TS101_HUMAN","experiments":10},{"accession1":"HGS_HUMAN","accession2":"UBC_HUMAN","experiments":10},{"accession1":"HGS_HUMAN","accession2":"NEDD4_HUMAN","experiments":4}]},{"accession":"ARF3_HUMAN","name":"ARF3_HUMAN","interactions":[{"accession1":"ARF3_HUMAN","accession2":"GGA3_HUMAN","experiments":3},{"accession1":"ARF3_HUMAN","accession2":"ARF1_HUMAN","experiments":1},{"accession1":"ARF3_HUMAN","accession2":"RS27A_HUMAN","experiments":1},{"accession1":"ARF3_HUMAN","accession2":"GGA3_HUMAN","experiments":3},{"accession1":"ARF3_HUMAN","accession2":"CYH2_HUMAN","experiments":1}]},{"accession":"CLCB_HUMAN","name":"CLCB_HUMAN","interactions":[{"accession1":"CLCB_HUMAN","accession2":"GGA3_HUMAN","experiments":1},{"accession1":"CLCB_HUMAN","accession2":"CLCA_HUMAN","experiments":4},{"accession1":"CLCB_HUMAN","accession2":"CLH1_HUMAN","experiments":4},{"accession1":"CLCB_HUMAN","accession2":"HGS_HUMAN","experiments":1},{"accession1":"CLCB_HUMAN","accession2":"UBB_HUMAN","experiments":2},{"accession1":"CLCB_HUMAN","accession2":"RAB5A_HUMAN","experiments":1},{"accession1":"CLCB_HUMAN","accession2":"ARF1_HUMAN","experiments":1},{"accession1":"CLCB_HUMAN","accession2":"RS27A_HUMAN","experiments":2},{"accession1":"CLCB_HUMAN","accession2":"ARF6_HUMAN","experiments":1},{"accession1":"CLCB_HUMAN","accession2":"GGA3_HUMAN","experiments":1},{"accession1":"CLCB_HUMAN","accession2":"RL40_HUMAN","experiments":2},{"accession1":"CLCB_HUMAN","accession2":"UBC_HUMAN","experiments":2}]},{"accession":"VPS18_HUMAN","name":"VPS18_HUMAN","interactions":[{"accession1":"VPS18_HUMAN","accession2":"GGA3_HUMAN","experiments":3},{"accession1":"VPS18_HUMAN","accession2":"RAB4A_HUMAN","experiments":1},{"accession1":"VPS18_HUMAN","accession2":"VPS11_HUMAN","experiments":10},{"accession1":"VPS18_HUMAN","accession2":"RAB5A_HUMAN","experiments":3},{"accession1":"VPS18_HUMAN","accession2":"GGA3_HUMAN","experiments":3}]},{"accession":"ADA2A_HUMAN","name":"ADA2A_HUMAN","interactions":[{"accession1":"ADA2A_HUMAN","accession2":"GGA3_HUMAN","experiments":1},{"accession1":"ADA2A_HUMAN","accession2":"ADA2A_HUMAN","experiments":6},{"accession1":"ADA2A_HUMAN","accession2":"GGA3_HUMAN","experiments":1}]},{"accession":"RAB4A_HUMAN","name":"RAB4A_HUMAN","interactions":[{"accession1":"RAB4A_HUMAN","accession2":"GGA3_HUMAN","experiments":1},{"accession1":"RAB4A_HUMAN","accession2":"HGS_HUMAN","experiments":1},{"accession1":"RAB4A_HUMAN","accession2":"VPS18_HUMAN","experiments":1},{"accession1":"RAB4A_HUMAN","accession2":"RAB4A_HUMAN","experiments":10},{"accession1":"RAB4A_HUMAN","accession2":"CRK_HUMAN","experiments":1},{"accession1":"RAB4A_HUMAN","accession2":"ITB1_HUMAN","experiments":1},{"accession1":"RAB4A_HUMAN","accession2":"RAB5A_HUMAN","experiments":2},{"accession1":"RAB4A_HUMAN","accession2":"ARF1_HUMAN","experiments":1},{"accession1":"RAB4A_HUMAN","accession2":"RS27A_HUMAN","experiments":1},{"accession1":"RAB4A_HUMAN","accession2":"ARF6_HUMAN","experiments":1},{"accession1":"RAB4A_HUMAN","accession2":"GGA3_HUMAN","experiments":1},{"accession1":"RAB4A_HUMAN","accession2":"RABE1_HUMAN","experiments":10}]},{"accession":"CRK_HUMAN","name":"CRK_HUMAN","interactions":[{"accession1":"CRK_HUMAN","accession2":"GGA3_HUMAN","experiments":2},{"accession1":"CRK_HUMAN","accession2":"RAB4A_HUMAN","experiments":1},{"accession1":"CRK_HUMAN","accession2":"CRK_HUMAN","experiments":6},{"accession1":"CRK_HUMAN","accession2":"ARF6_HUMAN","experiments":1},{"accession1":"CRK_HUMAN","accession2":"GGA3_HUMAN","experiments":2},{"accession1":"CRK_HUMAN","accession2":"TS101_HUMAN","experiments":2},{"accession1":"CRK_HUMAN","accession2":"UBC_HUMAN","experiments":1}]},{"accession":"VPS11_HUMAN","name":"VPS11_HUMAN","interactions":[{"accession1":"VPS11_HUMAN","accession2":"GGA3_HUMAN","experiments":1},{"accession1":"VPS11_HUMAN","accession2":"VPS18_HUMAN","experiments":10},{"accession1":"VPS11_HUMAN","accession2":"RAB5A_HUMAN","experiments":1},{"accession1":"VPS11_HUMAN","accession2":"GGA3_HUMAN","experiments":1},{"accession1":"VPS11_HUMAN","accession2":"TS101_HUMAN","experiments":2}]},{"accession":"ITB1_HUMAN","name":"ITB1_HUMAN","interactions":[{"accession1":"ITB1_HUMAN","accession2":"GGA3_HUMAN","experiments":2},{"accession1":"ITB1_HUMAN","accession2":"RAB4A_HUMAN","experiments":1},{"accession1":"ITB1_HUMAN","accession2":"ITB1_HUMAN","experiments":10},{"accession1":"ITB1_HUMAN","accession2":"RAB5A_HUMAN","experiments":2},{"accession1":"ITB1_HUMAN","accession2":"ARF6_HUMAN","experiments":1},{"accession1":"ITB1_HUMAN","accession2":"GGA3_HUMAN","experiments":2}]},{"accession":"UBB_HUMAN","name":"UBB_HUMAN","interactions":[{"accession1":"UBB_HUMAN","accession2":"GGA3_HUMAN","experiments":4},{"accession1":"UBB_HUMAN","accession2":"CLCA_HUMAN","experiments":1},{"accession1":"UBB_HUMAN","accession2":"HGS_HUMAN","experiments":1},{"accession1":"UBB_HUMAN","accession2":"CLCB_HUMAN","experiments":1},{"accession1":"UBB_HUMAN","accession2":"UBB_HUMAN","experiments":10},{"accession1":"UBB_HUMAN","accession2":"RAB5A_HUMAN","experiments":1},{"accession1":"UBB_HUMAN","accession2":"RS27A_HUMAN","experiments":2},{"accession1":"UBB_HUMAN","accession2":"GGA3_HUMAN","experiments":3},{"accession1":"UBB_HUMAN","accession2":"RL40_HUMAN","experiments":10},{"accession1":"UBB_HUMAN","accession2":"TS101_HUMAN","experiments":4},{"accession1":"UBB_HUMAN","accession2":"UBC_HUMAN","experiments":4},{"accession1":"UBB_HUMAN","accession2":"NEDD4_HUMAN","experiments":3}]},{"accession":"TOLIP_HUMAN","name":"TOLIP_HUMAN","interactions":[{"accession1":"TOLIP_HUMAN","accession2":"GGA3_HUMAN","experiments":1},{"accession1":"TOLIP_HUMAN","accession2":"TOLIP_HUMAN","experiments":7},{"accession1":"TOLIP_HUMAN","accession2":"GGA3_HUMAN","experiments":1},{"accession1":"TOLIP_HUMAN","accession2":"UBC_HUMAN","experiments":9}]},{"accession":"RAB5A_HUMAN","name":"RAB5A_HUMAN","interactions":[{"accession1":"RAB5A_HUMAN","accession2":"GGA3_HUMAN","experiments":1},{"accession1":"RAB5A_HUMAN","accession2":"CLCA_HUMAN","experiments":1},{"accession1":"RAB5A_HUMAN","accession2":"HGS_HUMAN","experiments":1},{"accession1":"RAB5A_HUMAN","accession2":"CLCB_HUMAN","experiments":1},{"accession1":"RAB5A_HUMAN","accession2":"VPS18_HUMAN","experiments":3},{"accession1":"RAB5A_HUMAN","accession2":"RAB4A_HUMAN","experiments":2},{"accession1":"RAB5A_HUMAN","accession2":"VPS11_HUMAN","experiments":1},{"accession1":"RAB5A_HUMAN","accession2":"ITB1_HUMAN","experiments":2},{"accession1":"RAB5A_HUMAN","accession2":"UBB_HUMAN","experiments":2},{"accession1":"RAB5A_HUMAN","accession2":"RAB5A_HUMAN","experiments":10},{"accession1":"RAB5A_HUMAN","accession2":"ARF1_HUMAN","experiments":1},{"accession1":"RAB5A_HUMAN","accession2":"RS27A_HUMAN","experiments":2},{"accession1":"RAB5A_HUMAN","accession2":"GGA3_HUMAN","experiments":1},{"accession1":"RAB5A_HUMAN","accession2":"RL40_HUMAN","experiments":2},{"accession1":"RAB5A_HUMAN","accession2":"TS101_HUMAN","experiments":1},{"accession1":"RAB5A_HUMAN","accession2":"RABE1_HUMAN","experiments":10},{"accession1":"RAB5A_HUMAN","accession2":"UBC_HUMAN","experiments":2}]},{"accession":"ARF1_HUMAN","name":"ARF1_HUMAN","interactions":[{"accession1":"ARF1_HUMAN","accession2":"GGA3_HUMAN","experiments":7},{"accession1":"ARF1_HUMAN","accession2":"CLCA_HUMAN","experiments":1},{"accession1":"ARF1_HUMAN","accession2":"CLH1_HUMAN","experiments":1},{"accession1":"ARF1_HUMAN","accession2":"ARF3_HUMAN","experiments":1},{"accession1":"ARF1_HUMAN","accession2":"CLCB_HUMAN","experiments":1},{"accession1":"ARF1_HUMAN","accession2":"RAB4A_HUMAN","experiments":1},{"accession1":"ARF1_HUMAN","accession2":"RAB5A_HUMAN","experiments":1},{"accession1":"ARF1_HUMAN","accession2":"ARF1_HUMAN","experiments":10},{"accession1":"ARF1_HUMAN","accession2":"ARF6_HUMAN","experiments":1},{"accession1":"ARF1_HUMAN","accession2":"GGA3_HUMAN","experiments":7},{"accession1":"ARF1_HUMAN","accession2":"CYH2_HUMAN","experiments":7},{"accession1":"ARF1_HUMAN","accession2":"RL40_HUMAN","experiments":1},{"accession1":"ARF1_HUMAN","accession2":"UBC_HUMAN","experiments":1}]},{"accession":"RS27A_HUMAN","name":"RS27A_HUMAN","interactions":[{"accession1":"RS27A_HUMAN","accession2":"GGA3_HUMAN","experiments":2},{"accession1":"RS27A_HUMAN","accession2":"CLCA_HUMAN","experiments":1},{"accession1":"RS27A_HUMAN","accession2":"HGS_HUMAN","experiments":1},{"accession1":"RS27A_HUMAN","accession2":"ARF3_HUMAN","experiments":1},{"accession1":"RS27A_HUMAN","accession2":"CLCB_HUMAN","experiments":1},{"accession1":"RS27A_HUMAN","accession2":"RAB4A_HUMAN","experiments":1},{"accession1":"RS27A_HUMAN","accession2":"UBB_HUMAN","experiments":2},{"accession1":"RS27A_HUMAN","accession2":"RAB5A_HUMAN","experiments":1},{"accession1":"RS27A_HUMAN","accession2":"RS27A_HUMAN","experiments":10},{"accession1":"RS27A_HUMAN","accession2":"RL40_HUMAN","experiments":3},{"accession1":"RS27A_HUMAN","accession2":"TS101_HUMAN","experiments":1},{"accession1":"RS27A_HUMAN","accession2":"UBC_HUMAN","experiments":2},{"accession1":"RS27A_HUMAN","accession2":"NEDD4_HUMAN","experiments":1}]},{"accession":"ARF6_HUMAN","name":"ARF6_HUMAN","interactions":[{"accession1":"ARF6_HUMAN","accession2":"GGA3_HUMAN","experiments":8},{"accession1":"ARF6_HUMAN","accession2":"CLCA_HUMAN","experiments":1},{"accession1":"ARF6_HUMAN","accession2":"CLH1_HUMAN","experiments":1},{"accession1":"ARF6_HUMAN","accession2":"CLCB_HUMAN","experiments":1},{"accession1":"ARF6_HUMAN","accession2":"RAB4A_HUMAN","experiments":1},{"accession1":"ARF6_HUMAN","accession2":"CRK_HUMAN","experiments":1},{"accession1":"ARF6_HUMAN","accession2":"ITB1_HUMAN","experiments":1},{"accession1":"ARF6_HUMAN","accession2":"ARF1_HUMAN","experiments":1},{"accession1":"ARF6_HUMAN","accession2":"ARF6_HUMAN","experiments":6},{"accession1":"ARF6_HUMAN","accession2":"GGA3_HUMAN","experiments":8},{"accession1":"ARF6_HUMAN","accession2":"CYH2_HUMAN","experiments":7},{"accession1":"ARF6_HUMAN","accession2":"RL40_HUMAN","experiments":1}]},{"accession":"GGA3_HUMAN","name":"GGA3_HUMAN","interactions":[{"accession1":"GGA3_HUMAN","accession2":"GGA3_HUMAN","experiments":10},{"accession1":"GGA3_HUMAN","accession2":"CLCA_HUMAN","experiments":1},{"accession1":"GGA3_HUMAN","accession2":"CLH1_HUMAN","experiments":1},{"accession1":"GGA3_HUMAN","accession2":"HGS_HUMAN","experiments":1},{"accession1":"GGA3_HUMAN","accession2":"ARF3_HUMAN","experiments":3},{"accession1":"GGA3_HUMAN","accession2":"CLCB_HUMAN","experiments":1},{"accession1":"GGA3_HUMAN","accession2":"VPS18_HUMAN","experiments":3},{"accession1":"GGA3_HUMAN","accession2":"ADA2A_HUMAN","experiments":1},{"accession1":"GGA3_HUMAN","accession2":"RAB4A_HUMAN","experiments":1},{"accession1":"GGA3_HUMAN","accession2":"CRK_HUMAN","experiments":2},{"accession1":"GGA3_HUMAN","accession2":"VPS11_HUMAN","experiments":1},{"accession1":"GGA3_HUMAN","accession2":"ITB1_HUMAN","experiments":2},{"accession1":"GGA3_HUMAN","accession2":"UBB_HUMAN","experiments":4},{"accession1":"GGA3_HUMAN","accession2":"TOLIP_HUMAN","experiments":1},{"accession1":"GGA3_HUMAN","accession2":"RAB5A_HUMAN","experiments":1},{"accession1":"GGA3_HUMAN","accession2":"ARF1_HUMAN","experiments":7},{"accession1":"GGA3_HUMAN","accession2":"RS27A_HUMAN","experiments":2},{"accession1":"GGA3_HUMAN","accession2":"ARF6_HUMAN","experiments":8},{"accession1":"GGA3_HUMAN","accession2":"GGA3_HUMAN","experiments":10},{"accession1":"GGA3_HUMAN","accession2":"CYH2_HUMAN","experiments":1},{"accession1":"GGA3_HUMAN","accession2":"RL40_HUMAN","experiments":2},{"accession1":"GGA3_HUMAN","accession2":"TS101_HUMAN","experiments":2},{"accession1":"GGA3_HUMAN","accession2":"RABE1_HUMAN","experiments":10},{"accession1":"GGA3_HUMAN","accession2":"UBC_HUMAN","experiments":10},{"accession1":"GGA3_HUMAN","accession2":"PACS1_HUMAN","experiments":9},{"accession1":"GGA3_HUMAN","accession2":"NEDD4_HUMAN","experiments":1}]},{"accession":"CYH2_HUMAN","name":"CYH2_HUMAN","interactions":[{"accession1":"CYH2_HUMAN","accession2":"GGA3_HUMAN","experiments":1},{"accession1":"CYH2_HUMAN","accession2":"ARF3_HUMAN","experiments":1},{"accession1":"CYH2_HUMAN","accession2":"ARF1_HUMAN","experiments":7},{"accession1":"CYH2_HUMAN","accession2":"ARF6_HUMAN","experiments":7},{"accession1":"CYH2_HUMAN","accession2":"GGA3_HUMAN","experiments":1}]},{"accession":"RL40_HUMAN","name":"RL40_HUMAN","interactions":[{"accession1":"RL40_HUMAN","accession2":"GGA3_HUMAN","experiments":2},{"accession1":"RL40_HUMAN","accession2":"CLCA_HUMAN","experiments":1},{"accession1":"RL40_HUMAN","accession2":"HGS_HUMAN","experiments":1},{"accession1":"RL40_HUMAN","accession2":"CLCB_HUMAN","experiments":1},{"accession1":"RL40_HUMAN","accession2":"UBB_HUMAN","experiments":10},{"accession1":"RL40_HUMAN","accession2":"RAB5A_HUMAN","experiments":1},{"accession1":"RL40_HUMAN","accession2":"ARF1_HUMAN","experiments":1},{"accession1":"RL40_HUMAN","accession2":"RS27A_HUMAN","experiments":3},{"accession1":"RL40_HUMAN","accession2":"ARF6_HUMAN","experiments":1},{"accession1":"RL40_HUMAN","accession2":"GGA3_HUMAN","experiments":1},{"accession1":"RL40_HUMAN","accession2":"RL40_HUMAN","experiments":10},{"accession1":"RL40_HUMAN","accession2":"TS101_HUMAN","experiments":1},{"accession1":"RL40_HUMAN","accession2":"UBC_HUMAN","experiments":2},{"accession1":"RL40_HUMAN","accession2":"NEDD4_HUMAN","experiments":1}]},{"accession":"TS101_HUMAN","name":"TS101_HUMAN","interactions":[{"accession1":"TS101_HUMAN","accession2":"GGA3_HUMAN","experiments":2},{"accession1":"TS101_HUMAN","accession2":"HGS_HUMAN","experiments":10},{"accession1":"TS101_HUMAN","accession2":"CRK_HUMAN","experiments":2},{"accession1":"TS101_HUMAN","accession2":"VPS11_HUMAN","experiments":2},{"accession1":"TS101_HUMAN","accession2":"UBB_HUMAN","experiments":5},{"accession1":"TS101_HUMAN","accession2":"RAB5A_HUMAN","experiments":1},{"accession1":"TS101_HUMAN","accession2":"RS27A_HUMAN","experiments":2},{"accession1":"TS101_HUMAN","accession2":"GGA3_HUMAN","experiments":2},{"accession1":"TS101_HUMAN","accession2":"RL40_HUMAN","experiments":2},{"accession1":"TS101_HUMAN","accession2":"TS101_HUMAN","experiments":10},{"accession1":"TS101_HUMAN","accession2":"UBC_HUMAN","experiments":10},{"accession1":"TS101_HUMAN","accession2":"NEDD4_HUMAN","experiments":2}]},{"accession":"RABE1_HUMAN","name":"RABE1_HUMAN","interactions":[{"accession1":"RABE1_HUMAN","accession2":"GGA3_HUMAN","experiments":10},{"accession1":"RABE1_HUMAN","accession2":"CLCA_HUMAN","experiments":1},{"accession1":"RABE1_HUMAN","accession2":"RAB4A_HUMAN","experiments":10},{"accession1":"RABE1_HUMAN","accession2":"RAB5A_HUMAN","experiments":10},{"accession1":"RABE1_HUMAN","accession2":"GGA3_HUMAN","experiments":10},{"accession1":"RABE1_HUMAN","accession2":"RABE1_HUMAN","experiments":10},{"accession1":"RABE1_HUMAN","accession2":"UBC_HUMAN","experiments":3}]},{"accession":"UBC_HUMAN","name":"UBC_HUMAN","interactions":[{"accession1":"UBC_HUMAN","accession2":"GGA3_HUMAN","experiments":10},{"accession1":"UBC_HUMAN","accession2":"CLCA_HUMAN","experiments":1},{"accession1":"UBC_HUMAN","accession2":"CLH1_HUMAN","experiments":1},{"accession1":"UBC_HUMAN","accession2":"HGS_HUMAN","experiments":10},{"accession1":"UBC_HUMAN","accession2":"CLCB_HUMAN","experiments":1},{"accession1":"UBC_HUMAN","accession2":"CRK_HUMAN","experiments":1},{"accession1":"UBC_HUMAN","accession2":"UBB_HUMAN","experiments":4},{"accession1":"UBC_HUMAN","accession2":"TOLIP_HUMAN","experiments":9},{"accession1":"UBC_HUMAN","accession2":"RAB5A_HUMAN","experiments":1},{"accession1":"UBC_HUMAN","accession2":"ARF1_HUMAN","experiments":1},{"accession1":"UBC_HUMAN","accession2":"RS27A_HUMAN","experiments":2},{"accession1":"UBC_HUMAN","accession2":"GGA3_HUMAN","experiments":10},{"accession1":"UBC_HUMAN","accession2":"RL40_HUMAN","experiments":2},{"accession1":"UBC_HUMAN","accession2":"TS101_HUMAN","experiments":10},{"accession1":"UBC_HUMAN","accession2":"RABE1_HUMAN","experiments":3},{"accession1":"UBC_HUMAN","accession2":"UBC_HUMAN","experiments":10},{"accession1":"UBC_HUMAN","accession2":"NEDD4_HUMAN","experiments":10}]},{"accession":"PACS1_HUMAN","name":"PACS1_HUMAN","interactions":[{"accession1":"PACS1_HUMAN","accession2":"GGA3_HUMAN","experiments":9},{"accession1":"PACS1_HUMAN","accession2":"GGA3_HUMAN","experiments":9}]},{"accession":"NEDD4_HUMAN","name":"NEDD4_HUMAN","interactions":[{"accession1":"NEDD4_HUMAN","accession2":"GGA3_HUMAN","experiments":1},{"accession1":"NEDD4_HUMAN","accession2":"HGS_HUMAN","experiments":4},{"accession1":"NEDD4_HUMAN","accession2":"UBB_HUMAN","experiments":5},{"accession1":"NEDD4_HUMAN","accession2":"RS27A_HUMAN","experiments":2},{"accession1":"NEDD4_HUMAN","accession2":"GGA3_HUMAN","experiments":1},{"accession1":"NEDD4_HUMAN","accession2":"RL40_HUMAN","experiments":2},{"accession1":"NEDD4_HUMAN","accession2":"TS101_HUMAN","experiments":2},{"accession1":"NEDD4_HUMAN","accession2":"UBC_HUMAN","experiments":10},{"accession1":"NEDD4_HUMAN","accession2":"NEDD4_HUMAN","experiments":10}]}]