[{"accession":"PLAK_HUMAN","name":"PLAK_HUMAN","interactions":[{"accession1":"PLAK_HUMAN","accession2":"ERBB2_HUMAN","experiments":3},{"accession1":"PLAK_HUMAN","accession2":"DLDH_HUMAN","experiments":2},{"accession1":"PLAK_HUMAN","accession2":"PEBP1_HUMAN","experiments":2},{"accession1":"PLAK_HUMAN","accession2":"CTNB1_HUMAN","experiments":10},{"accession1":"PLAK_HUMAN","accession2":"CADH1_HUMAN","experiments":10},{"accession1":"PLAK_HUMAN","accession2":"RASK_HUMAN","experiments":2},{"accession1":"PLAK_HUMAN","accession2":"APC_HUMAN","experiments":9},{"accession1":"PLAK_HUMAN","accession2":"RAB5A_HUMAN","experiments":2},{"accession1":"PLAK_HUMAN","accession2":"CADH2_HUMAN","experiments":6},{"accession1":"PLAK_HUMAN","accession2":"DESP_HUMAN","experiments":8},{"accession1":"PLAK_HUMAN","accession2":"CTNA1_HUMAN","experiments":10},{"accession1":"PLAK_HUMAN","accession2":"DREB_HUMAN","experiments":2},{"accession1":"PLAK_HUMAN","accession2":"DDX6_HUMAN","experiments":3},{"accession1":"PLAK_HUMAN","accession2":"SYNPO_HUMAN","experiments":2},{"accession1":"PLAK_HUMAN","accession2":"DSG1_HUMAN","experiments":6}]},{"accession":"ERBB2_HUMAN","name":"ERBB2_HUMAN","interactions":[{"accession1":"ERBB2_HUMAN","accession2":"PLAK_HUMAN","experiments":3},{"accession1":"ERBB2_HUMAN","accession2":"ERBB2_HUMAN","experiments":10},{"accession1":"ERBB2_HUMAN","accession2":"PEBP1_HUMAN","experiments":2},{"accession1":"ERBB2_HUMAN","accession2":"CTNB1_HUMAN","experiments":7},{"accession1":"ERBB2_HUMAN","accession2":"CADH1_HUMAN","experiments":1},{"accession1":"ERBB2_HUMAN","accession2":"RASK_HUMAN","experiments":1},{"accession1":"ERBB2_HUMAN","accession2":"CADH2_HUMAN","experiments":2},{"accession1":"ERBB2_HUMAN","accession2":"DDX6_HUMAN","experiments":1}]},{"accession":"DLDH_HUMAN","name":"DLDH_HUMAN","interactions":[{"accession1":"DLDH_HUMAN","accession2":"PLAK_HUMAN","experiments":2},{"accession1":"DLDH_HUMAN","accession2":"DLDH_HUMAN","experiments":10},{"accession1":"DLDH_HUMAN","accession2":"DESP_HUMAN","experiments":3},{"accession1":"DLDH_HUMAN","accession2":"CTNA1_HUMAN","experiments":2},{"accession1":"DLDH_HUMAN","accession2":"SYNPO_HUMAN","experiments":1}]},{"accession":"PEBP1_HUMAN","name":"PEBP1_HUMAN","interactions":[{"accession1":"PEBP1_HUMAN","accession2":"PLAK_HUMAN","experiments":2},{"accession1":"PEBP1_HUMAN","accession2":"ERBB2_HUMAN","experiments":2},{"accession1":"PEBP1_HUMAN","accession2":"PEBP1_HUMAN","experiments":9},{"accession1":"PEBP1_HUMAN","accession2":"RASK_HUMAN","experiments":1},{"accession1":"PEBP1_HUMAN","accession2":"DESP_HUMAN","experiments":2},{"accession1":"PEBP1_HUMAN","accession2":"DSG1_HUMAN","experiments":2}]},{"accession":"CTNB1_HUMAN","name":"CTNB1_HUMAN","interactions":[{"accession1":"CTNB1_HUMAN","accession2":"PLAK_HUMAN","experiments":10},{"accession1":"CTNB1_HUMAN","accession2":"ERBB2_HUMAN","experiments":7},{"accession1":"CTNB1_HUMAN","accession2":"CTNB1_HUMAN","experiments":10},{"accession1":"CTNB1_HUMAN","accession2":"CADH1_HUMAN","experiments":10},{"accession1":"CTNB1_HUMAN","accession2":"RASK_HUMAN","experiments":3},{"accession1":"CTNB1_HUMAN","accession2":"APC_HUMAN","experiments":10},{"accession1":"CTNB1_HUMAN","accession2":"RAB5A_HUMAN","experiments":1},{"accession1":"CTNB1_HUMAN","accession2":"CADH2_HUMAN","experiments":10},{"accession1":"CTNB1_HUMAN","accession2":"CTNA1_HUMAN","experiments":10},{"accession1":"CTNB1_HUMAN","accession2":"SYNPO_HUMAN","experiments":1}]},{"accession":"CADH1_HUMAN","name":"CADH1_HUMAN","interactions":[{"accession1":"CADH1_HUMAN","accession2":"PLAK_HUMAN","experiments":10},{"accession1":"CADH1_HUMAN","accession2":"ERBB2_HUMAN","experiments":1},{"accession1":"CADH1_HUMAN","accession2":"CTNB1_HUMAN","experiments":10},{"accession1":"CADH1_HUMAN","accession2":"CADH1_HUMAN","experiments":10},{"accession1":"CADH1_HUMAN","accession2":"RASK_HUMAN","experiments":1},{"accession1":"CADH1_HUMAN","accession2":"APC_HUMAN","experiments":1},{"accession1":"CADH1_HUMAN","accession2":"RAB5A_HUMAN","experiments":1},{"accession1":"CADH1_HUMAN","accession2":"CADH2_HUMAN","experiments":1},{"accession1":"CADH1_HUMAN","accession2":"CTNA1_HUMAN","experiments":10},{"accession1":"CADH1_HUMAN","accession2":"DREB_HUMAN","experiments":1},{"accession1":"CADH1_HUMAN","accession2":"DDX6_HUMAN","experiments":1}]},{"accession":"RASK_HUMAN","name":"RASK_HUMAN","interactions":[{"accession1":"RASK_HUMAN","accession2":"PLAK_HUMAN","experiments":2},{"accession1":"RASK_HUMAN","accession2":"ERBB2_HUMAN","experiments":1},{"accession1":"RASK_HUMAN","accession2":"PEBP1_HUMAN","experiments":1},{"accession1":"RASK_HUMAN","accession2":"CTNB1_HUMAN","experiments":3},{"accession1":"RASK_HUMAN","accession2":"CADH1_HUMAN","experiments":1},{"accession1":"RASK_HUMAN","accession2":"RASK_HUMAN","experiments":10},{"accession1":"RASK_HUMAN","accession2":"CTNA1_HUMAN","experiments":2}]},{"accession":"APC_HUMAN","name":"APC_HUMAN","interactions":[{"accession1":"APC_HUMAN","accession2":"PLAK_HUMAN","experiments":9},{"accession1":"APC_HUMAN","accession2":"CTNB1_HUMAN","experiments":10},{"accession1":"APC_HUMAN","accession2":"CADH1_HUMAN","experiments":1},{"accession1":"APC_HUMAN","accession2":"APC_HUMAN","experiments":10},{"accession1":"APC_HUMAN","accession2":"CTNA1_HUMAN","experiments":10},{"accession1":"APC_HUMAN","accession2":"SYNPO_HUMAN","experiments":2}]},{"accession":"RAB5A_HUMAN","name":"RAB5A_HUMAN","interactions":[{"accession1":"RAB5A_HUMAN","accession2":"PLAK_HUMAN","experiments":2},{"accession1":"RAB5A_HUMAN","accession2":"CTNB1_HUMAN","experiments":1},{"accession1":"RAB5A_HUMAN","accession2":"CADH1_HUMAN","experiments":1},{"accession1":"RAB5A_HUMAN","accession2":"RAB5A_HUMAN","experiments":10},{"accession1":"RAB5A_HUMAN","accession2":"CTNA1_HUMAN","experiments":1},{"accession1":"RAB5A_HUMAN","accession2":"DREB_HUMAN","experiments":2}]},{"accession":"CADH2_HUMAN","name":"CADH2_HUMAN","interactions":[{"accession1":"CADH2_HUMAN","accession2":"PLAK_HUMAN","experiments":6},{"accession1":"CADH2_HUMAN","accession2":"ERBB2_HUMAN","experiments":2},{"accession1":"CADH2_HUMAN","accession2":"CTNB1_HUMAN","experiments":10},{"accession1":"CADH2_HUMAN","accession2":"CADH1_HUMAN","experiments":1},{"accession1":"CADH2_HUMAN","accession2":"CADH2_HUMAN","experiments":10},{"accession1":"CADH2_HUMAN","accession2":"CTNA1_HUMAN","experiments":4},{"accession1":"CADH2_HUMAN","accession2":"DREB_HUMAN","experiments":1}]},{"accession":"DESP_HUMAN","name":"DESP_HUMAN","interactions":[{"accession1":"DESP_HUMAN","accession2":"PLAK_HUMAN","experiments":8},{"accession1":"DESP_HUMAN","accession2":"DLDH_HUMAN","experiments":3},{"accession1":"DESP_HUMAN","accession2":"PEBP1_HUMAN","experiments":2},{"accession1":"DESP_HUMAN","accession2":"DESP_HUMAN","experiments":8},{"accession1":"DESP_HUMAN","accession2":"SYNPO_HUMAN","experiments":1},{"accession1":"DESP_HUMAN","accession2":"DSG1_HUMAN","experiments":3}]},{"accession":"CTNA1_HUMAN","name":"CTNA1_HUMAN","interactions":[{"accession1":"CTNA1_HUMAN","accession2":"PLAK_HUMAN","experiments":10},{"accession1":"CTNA1_HUMAN","accession2":"DLDH_HUMAN","experiments":2},{"accession1":"CTNA1_HUMAN","accession2":"CTNB1_HUMAN","experiments":10},{"accession1":"CTNA1_HUMAN","accession2":"CADH1_HUMAN","experiments":10},{"accession1":"CTNA1_HUMAN","accession2":"RASK_HUMAN","experiments":2},{"accession1":"CTNA1_HUMAN","accession2":"APC_HUMAN","experiments":10},{"accession1":"CTNA1_HUMAN","accession2":"RAB5A_HUMAN","experiments":1},{"accession1":"CTNA1_HUMAN","accession2":"CADH2_HUMAN","experiments":4},{"accession1":"CTNA1_HUMAN","accession2":"CTNA1_HUMAN","experiments":10},{"accession1":"CTNA1_HUMAN","accession2":"SYNPO_HUMAN","experiments":1}]},{"accession":"DREB_HUMAN","name":"DREB_HUMAN","interactions":[{"accession1":"DREB_HUMAN","accession2":"PLAK_HUMAN","experiments":2},{"accession1":"DREB_HUMAN","accession2":"CADH1_HUMAN","experiments":1},{"accession1":"DREB_HUMAN","accession2":"RAB5A_HUMAN","experiments":2},{"accession1":"DREB_HUMAN","accession2":"CADH2_HUMAN","experiments":1},{"accession1":"DREB_HUMAN","accession2":"DREB_HUMAN","experiments":6},{"accession1":"DREB_HUMAN","accession2":"SYNPO_HUMAN","experiments":2}]},{"accession":"DDX6_HUMAN","name":"DDX6_HUMAN","interactions":[{"accession1":"DDX6_HUMAN","accession2":"PLAK_HUMAN","experiments":3},{"accession1":"DDX6_HUMAN","accession2":"ERBB2_HUMAN","experiments":1},{"accession1":"DDX6_HUMAN","accession2":"CADH1_HUMAN","experiments":1},{"accession1":"DDX6_HUMAN","accession2":"DDX6_HUMAN","experiments":10}]},{"accession":"SYNPO_HUMAN","name":"SYNPO_HUMAN","interactions":[{"accession1":"SYNPO_HUMAN","accession2":"PLAK_HUMAN","experiments":2},{"accession1":"SYNPO_HUMAN","accession2":"DLDH_HUMAN","experiments":1},{"accession1":"SYNPO_HUMAN","accession2":"CTNB1_HUMAN","experiments":1},{"accession1":"SYNPO_HUMAN","accession2":"APC_HUMAN","experiments":2},{"accession1":"SYNPO_HUMAN","accession2":"DESP_HUMAN","experiments":1},{"accession1":"SYNPO_HUMAN","accession2":"CTNA1_HUMAN","experiments":1},{"accession1":"SYNPO_HUMAN","accession2":"DREB_HUMAN","experiments":2}]},{"accession":"DSG1_HUMAN","name":"DSG1_HUMAN","interactions":[{"accession1":"DSG1_HUMAN","accession2":"PLAK_HUMAN","experiments":6},{"accession1":"DSG1_HUMAN","accession2":"PEBP1_HUMAN","experiments":2},{"accession1":"DSG1_HUMAN","accession2":"DESP_HUMAN","experiments":3}]}]