[{"accession":"RHG26_HUMAN","name":"RHG26_HUMAN","interactions":[{"accession1":"RHG26_HUMAN","accession2":"CDC42_HUMAN","experiments":1},{"accession1":"RHG26_HUMAN","accession2":"NRX1A_HUMAN","experiments":2},{"accession1":"RHG26_HUMAN","accession2":"KC1E_HUMAN","experiments":2},{"accession1":"RHG26_HUMAN","accession2":"RHG21_HUMAN","experiments":1},{"accession1":"RHG26_HUMAN","accession2":"NCK2_HUMAN","experiments":1},{"accession1":"RHG26_HUMAN","accession2":"DOCK1_HUMAN","experiments":1},{"accession1":"RHG26_HUMAN","accession2":"ARHG2_HUMAN","experiments":1},{"accession1":"RHG26_HUMAN","accession2":"RPGF4_HUMAN","experiments":1},{"accession1":"RHG26_HUMAN","accession2":"P5CR1_HUMAN","experiments":2},{"accession1":"RHG26_HUMAN","accession2":"GCR_HUMAN","experiments":1},{"accession1":"RHG26_HUMAN","accession2":"SOS1_HUMAN","experiments":1},{"accession1":"RHG26_HUMAN","accession2":"MARE2_HUMAN","experiments":2},{"accession1":"RHG26_HUMAN","accession2":"SRBS2_HUMAN","experiments":1},{"accession1":"RHG26_HUMAN","accession2":"PDLI5_HUMAN","experiments":1},{"accession1":"RHG26_HUMAN","accession2":"PRIC2_HUMAN","experiments":1},{"accession1":"RHG26_HUMAN","accession2":"FAK1_HUMAN","experiments":2},{"accession1":"RHG26_HUMAN","accession2":"PTEN_HUMAN","experiments":1},{"accession1":"RHG26_HUMAN","accession2":"CAH2_HUMAN","experiments":2},{"accession1":"RHG26_HUMAN","accession2":"RBP1_HUMAN","experiments":1},{"accession1":"RHG26_HUMAN","accession2":"FGD4_HUMAN","experiments":1},{"accession1":"RHG26_HUMAN","accession2":"SRBS1_HUMAN","experiments":1},{"accession1":"RHG26_HUMAN","accession2":"RPGF2_HUMAN","experiments":1},{"accession1":"RHG26_HUMAN","accession2":"SLMAP_HUMAN","experiments":1},{"accession1":"RHG26_HUMAN","accession2":"OPHN1_HUMAN","experiments":2},{"accession1":"RHG26_HUMAN","accession2":"EPS8_HUMAN","experiments":1},{"accession1":"RHG26_HUMAN","accession2":"DAB2P_HUMAN","experiments":1},{"accession1":"RHG26_HUMAN","accession2":"SC6A4_HUMAN","experiments":1},{"accession1":"RHG26_HUMAN","accession2":"RFIP5_HUMAN","experiments":2},{"accession1":"RHG26_HUMAN","accession2":"RHOA_HUMAN","experiments":2},{"accession1":"RHG26_HUMAN","accession2":"ANS1B_HUMAN","experiments":1},{"accession1":"RHG26_HUMAN","accession2":"DMD_HUMAN","experiments":1},{"accession1":"RHG26_HUMAN","accession2":"SRGP2_HUMAN","experiments":1},{"accession1":"RHG26_HUMAN","accession2":"SYGP1_HUMAN","experiments":1},{"accession1":"RHG26_HUMAN","accession2":"KC1D_HUMAN","experiments":2}]},{"accession":"CDC42_HUMAN","name":"CDC42_HUMAN","interactions":[{"accession1":"CDC42_HUMAN","accession2":"RHG26_HUMAN","experiments":1},{"accession1":"CDC42_HUMAN","accession2":"CDC42_HUMAN","experiments":10},{"accession1":"CDC42_HUMAN","accession2":"RHG21_HUMAN","experiments":1},{"accession1":"CDC42_HUMAN","accession2":"NCK2_HUMAN","experiments":1},{"accession1":"CDC42_HUMAN","accession2":"DOCK1_HUMAN","experiments":1},{"accession1":"CDC42_HUMAN","accession2":"FAK1_HUMAN","experiments":1},{"accession1":"CDC42_HUMAN","accession2":"PTEN_HUMAN","experiments":1},{"accession1":"CDC42_HUMAN","accession2":"RBP1_HUMAN","experiments":1},{"accession1":"CDC42_HUMAN","accession2":"FGD4_HUMAN","experiments":1},{"accession1":"CDC42_HUMAN","accession2":"OPHN1_HUMAN","experiments":2},{"accession1":"CDC42_HUMAN","accession2":"EPS8_HUMAN","experiments":1},{"accession1":"CDC42_HUMAN","accession2":"SC6A4_HUMAN","experiments":1},{"accession1":"CDC42_HUMAN","accession2":"RFIP5_HUMAN","experiments":1},{"accession1":"CDC42_HUMAN","accession2":"RHOA_HUMAN","experiments":2},{"accession1":"CDC42_HUMAN","accession2":"SRGP2_HUMAN","experiments":1}]},{"accession":"NRX1A_HUMAN","name":"NRX1A_HUMAN","interactions":[{"accession1":"NRX1A_HUMAN","accession2":"RHG26_HUMAN","experiments":2},{"accession1":"NRX1A_HUMAN","accession2":"NRX1A_HUMAN","experiments":2}]},{"accession":"KC1E_HUMAN","name":"KC1E_HUMAN","interactions":[{"accession1":"KC1E_HUMAN","accession2":"RHG26_HUMAN","experiments":2},{"accession1":"KC1E_HUMAN","accession2":"KC1E_HUMAN","experiments":6},{"accession1":"KC1E_HUMAN","accession2":"RHG21_HUMAN","experiments":1},{"accession1":"KC1E_HUMAN","accession2":"CAH2_HUMAN","experiments":1},{"accession1":"KC1E_HUMAN","accession2":"SC6A4_HUMAN","experiments":1},{"accession1":"KC1E_HUMAN","accession2":"KC1D_HUMAN","experiments":6}]},{"accession":"RHG21_HUMAN","name":"RHG21_HUMAN","interactions":[{"accession1":"RHG21_HUMAN","accession2":"RHG26_HUMAN","experiments":1},{"accession1":"RHG21_HUMAN","accession2":"CDC42_HUMAN","experiments":1},{"accession1":"RHG21_HUMAN","accession2":"KC1E_HUMAN","experiments":1},{"accession1":"RHG21_HUMAN","accession2":"NCK2_HUMAN","experiments":1},{"accession1":"RHG21_HUMAN","accession2":"DOCK1_HUMAN","experiments":1},{"accession1":"RHG21_HUMAN","accession2":"ARHG2_HUMAN","experiments":1},{"accession1":"RHG21_HUMAN","accession2":"SRBS2_HUMAN","experiments":1},{"accession1":"RHG21_HUMAN","accession2":"PDLI5_HUMAN","experiments":1},{"accession1":"RHG21_HUMAN","accession2":"PRIC2_HUMAN","experiments":1},{"accession1":"RHG21_HUMAN","accession2":"RBP1_HUMAN","experiments":1},{"accession1":"RHG21_HUMAN","accession2":"FGD4_HUMAN","experiments":1},{"accession1":"RHG21_HUMAN","accession2":"SRBS1_HUMAN","experiments":1},{"accession1":"RHG21_HUMAN","accession2":"SLMAP_HUMAN","experiments":1},{"accession1":"RHG21_HUMAN","accession2":"EPS8_HUMAN","experiments":1},{"accession1":"RHG21_HUMAN","accession2":"DAB2P_HUMAN","experiments":1},{"accession1":"RHG21_HUMAN","accession2":"SC6A4_HUMAN","experiments":1},{"accession1":"RHG21_HUMAN","accession2":"RHOA_HUMAN","experiments":2},{"accession1":"RHG21_HUMAN","accession2":"SRGP2_HUMAN","experiments":1},{"accession1":"RHG21_HUMAN","accession2":"SYGP1_HUMAN","experiments":1},{"accession1":"RHG21_HUMAN","accession2":"KC1D_HUMAN","experiments":1}]},{"accession":"NCK2_HUMAN","name":"NCK2_HUMAN","interactions":[{"accession1":"NCK2_HUMAN","accession2":"RHG26_HUMAN","experiments":1},{"accession1":"NCK2_HUMAN","accession2":"CDC42_HUMAN","experiments":1},{"accession1":"NCK2_HUMAN","accession2":"RHG21_HUMAN","experiments":1},{"accession1":"NCK2_HUMAN","accession2":"NCK2_HUMAN","experiments":5},{"accession1":"NCK2_HUMAN","accession2":"DOCK1_HUMAN","experiments":4},{"accession1":"NCK2_HUMAN","accession2":"SOS1_HUMAN","experiments":1},{"accession1":"NCK2_HUMAN","accession2":"SRBS2_HUMAN","experiments":4},{"accession1":"NCK2_HUMAN","accession2":"PRIC2_HUMAN","experiments":1},{"accession1":"NCK2_HUMAN","accession2":"FAK1_HUMAN","experiments":3},{"accession1":"NCK2_HUMAN","accession2":"SRBS1_HUMAN","experiments":2},{"accession1":"NCK2_HUMAN","accession2":"ANS1B_HUMAN","experiments":1},{"accession1":"NCK2_HUMAN","accession2":"SYGP1_HUMAN","experiments":4}]},{"accession":"DOCK1_HUMAN","name":"DOCK1_HUMAN","interactions":[{"accession1":"DOCK1_HUMAN","accession2":"RHG26_HUMAN","experiments":1},{"accession1":"DOCK1_HUMAN","accession2":"CDC42_HUMAN","experiments":1},{"accession1":"DOCK1_HUMAN","accession2":"RHG21_HUMAN","experiments":1},{"accession1":"DOCK1_HUMAN","accession2":"NCK2_HUMAN","experiments":4},{"accession1":"DOCK1_HUMAN","accession2":"DOCK1_HUMAN","experiments":2},{"accession1":"DOCK1_HUMAN","accession2":"RPGF4_HUMAN","experiments":1},{"accession1":"DOCK1_HUMAN","accession2":"SOS1_HUMAN","experiments":1},{"accession1":"DOCK1_HUMAN","accession2":"PDLI5_HUMAN","experiments":1},{"accession1":"DOCK1_HUMAN","accession2":"PRIC2_HUMAN","experiments":1},{"accession1":"DOCK1_HUMAN","accession2":"FAK1_HUMAN","experiments":1},{"accession1":"DOCK1_HUMAN","accession2":"RBP1_HUMAN","experiments":1},{"accession1":"DOCK1_HUMAN","accession2":"FGD4_HUMAN","experiments":1},{"accession1":"DOCK1_HUMAN","accession2":"RHOA_HUMAN","experiments":1},{"accession1":"DOCK1_HUMAN","accession2":"DMD_HUMAN","experiments":1},{"accession1":"DOCK1_HUMAN","accession2":"SRGP2_HUMAN","experiments":1},{"accession1":"DOCK1_HUMAN","accession2":"SYGP1_HUMAN","experiments":1}]},{"accession":"ARHG2_HUMAN","name":"ARHG2_HUMAN","interactions":[{"accession1":"ARHG2_HUMAN","accession2":"RHG26_HUMAN","experiments":1},{"accession1":"ARHG2_HUMAN","accession2":"RHG21_HUMAN","experiments":1},{"accession1":"ARHG2_HUMAN","accession2":"ARHG2_HUMAN","experiments":2},{"accession1":"ARHG2_HUMAN","accession2":"GCR_HUMAN","experiments":1},{"accession1":"ARHG2_HUMAN","accession2":"PDLI5_HUMAN","experiments":1},{"accession1":"ARHG2_HUMAN","accession2":"PRIC2_HUMAN","experiments":1},{"accession1":"ARHG2_HUMAN","accession2":"FAK1_HUMAN","experiments":1},{"accession1":"ARHG2_HUMAN","accession2":"FGD4_HUMAN","experiments":1},{"accession1":"ARHG2_HUMAN","accession2":"SRBS1_HUMAN","experiments":1},{"accession1":"ARHG2_HUMAN","accession2":"EPS8_HUMAN","experiments":1},{"accession1":"ARHG2_HUMAN","accession2":"DAB2P_HUMAN","experiments":1},{"accession1":"ARHG2_HUMAN","accession2":"RHOA_HUMAN","experiments":10},{"accession1":"ARHG2_HUMAN","accession2":"SYGP1_HUMAN","experiments":1}]},{"accession":"RPGF4_HUMAN","name":"RPGF4_HUMAN","interactions":[{"accession1":"RPGF4_HUMAN","accession2":"RHG26_HUMAN","experiments":1},{"accession1":"RPGF4_HUMAN","accession2":"DOCK1_HUMAN","experiments":1},{"accession1":"RPGF4_HUMAN","accession2":"SOS1_HUMAN","experiments":1},{"accession1":"RPGF4_HUMAN","accession2":"PDLI5_HUMAN","experiments":1},{"accession1":"RPGF4_HUMAN","accession2":"PRIC2_HUMAN","experiments":1},{"accession1":"RPGF4_HUMAN","accession2":"RPGF2_HUMAN","experiments":1},{"accession1":"RPGF4_HUMAN","accession2":"SRGP2_HUMAN","experiments":1}]},{"accession":"P5CR1_HUMAN","name":"P5CR1_HUMAN","interactions":[{"accession1":"P5CR1_HUMAN","accession2":"RHG26_HUMAN","experiments":2},{"accession1":"P5CR1_HUMAN","accession2":"P5CR1_HUMAN","experiments":10},{"accession1":"P5CR1_HUMAN","accession2":"GCR_HUMAN","experiments":2}]},{"accession":"GCR_HUMAN","name":"GCR_HUMAN","interactions":[{"accession1":"GCR_HUMAN","accession2":"RHG26_HUMAN","experiments":1},{"accession1":"GCR_HUMAN","accession2":"ARHG2_HUMAN","experiments":1},{"accession1":"GCR_HUMAN","accession2":"P5CR1_HUMAN","experiments":2},{"accession1":"GCR_HUMAN","accession2":"GCR_HUMAN","experiments":10},{"accession1":"GCR_HUMAN","accession2":"RFIP5_HUMAN","experiments":1},{"accession1":"GCR_HUMAN","accession2":"RHOA_HUMAN","experiments":1}]},{"accession":"SOS1_HUMAN","name":"SOS1_HUMAN","interactions":[{"accession1":"SOS1_HUMAN","accession2":"RHG26_HUMAN","experiments":1},{"accession1":"SOS1_HUMAN","accession2":"NCK2_HUMAN","experiments":1},{"accession1":"SOS1_HUMAN","accession2":"DOCK1_HUMAN","experiments":1},{"accession1":"SOS1_HUMAN","accession2":"RPGF4_HUMAN","experiments":1},{"accession1":"SOS1_HUMAN","accession2":"SOS1_HUMAN","experiments":2},{"accession1":"SOS1_HUMAN","accession2":"PDLI5_HUMAN","experiments":1},{"accession1":"SOS1_HUMAN","accession2":"PRIC2_HUMAN","experiments":1},{"accession1":"SOS1_HUMAN","accession2":"FAK1_HUMAN","experiments":1},{"accession1":"SOS1_HUMAN","accession2":"SRBS1_HUMAN","experiments":1},{"accession1":"SOS1_HUMAN","accession2":"RPGF2_HUMAN","experiments":1},{"accession1":"SOS1_HUMAN","accession2":"EPS8_HUMAN","experiments":5},{"accession1":"SOS1_HUMAN","accession2":"DAB2P_HUMAN","experiments":1},{"accession1":"SOS1_HUMAN","accession2":"DMD_HUMAN","experiments":1}]},{"accession":"MARE2_HUMAN","name":"MARE2_HUMAN","interactions":[{"accession1":"MARE2_HUMAN","accession2":"RHG26_HUMAN","experiments":2},{"accession1":"MARE2_HUMAN","accession2":"MARE2_HUMAN","experiments":10},{"accession1":"MARE2_HUMAN","accession2":"SC6A4_HUMAN","experiments":1},{"accession1":"MARE2_HUMAN","accession2":"ANS1B_HUMAN","experiments":1}]},{"accession":"SRBS2_HUMAN","name":"SRBS2_HUMAN","interactions":[{"accession1":"SRBS2_HUMAN","accession2":"RHG26_HUMAN","experiments":1},{"accession1":"SRBS2_HUMAN","accession2":"RHG21_HUMAN","experiments":1},{"accession1":"SRBS2_HUMAN","accession2":"NCK2_HUMAN","experiments":4},{"accession1":"SRBS2_HUMAN","accession2":"SRBS2_HUMAN","experiments":5},{"accession1":"SRBS2_HUMAN","accession2":"PDLI5_HUMAN","experiments":1},{"accession1":"SRBS2_HUMAN","accession2":"PRIC2_HUMAN","experiments":1},{"accession1":"SRBS2_HUMAN","accession2":"SRBS1_HUMAN","experiments":1},{"accession1":"SRBS2_HUMAN","accession2":"OPHN1_HUMAN","experiments":1},{"accession1":"SRBS2_HUMAN","accession2":"EPS8_HUMAN","experiments":1},{"accession1":"SRBS2_HUMAN","accession2":"SC6A4_HUMAN","experiments":1},{"accession1":"SRBS2_HUMAN","accession2":"SRGP2_HUMAN","experiments":1},{"accession1":"SRBS2_HUMAN","accession2":"SYGP1_HUMAN","experiments":1}]},{"accession":"PDLI5_HUMAN","name":"PDLI5_HUMAN","interactions":[{"accession1":"PDLI5_HUMAN","accession2":"RHG26_HUMAN","experiments":1},{"accession1":"PDLI5_HUMAN","accession2":"RHG21_HUMAN","experiments":1},{"accession1":"PDLI5_HUMAN","accession2":"DOCK1_HUMAN","experiments":1},{"accession1":"PDLI5_HUMAN","accession2":"ARHG2_HUMAN","experiments":1},{"accession1":"PDLI5_HUMAN","accession2":"RPGF4_HUMAN","experiments":1},{"accession1":"PDLI5_HUMAN","accession2":"SOS1_HUMAN","experiments":1},{"accession1":"PDLI5_HUMAN","accession2":"SRBS2_HUMAN","experiments":1},{"accession1":"PDLI5_HUMAN","accession2":"PRIC2_HUMAN","experiments":1},{"accession1":"PDLI5_HUMAN","accession2":"RBP1_HUMAN","experiments":2},{"accession1":"PDLI5_HUMAN","accession2":"FGD4_HUMAN","experiments":1},{"accession1":"PDLI5_HUMAN","accession2":"SRBS1_HUMAN","experiments":1},{"accession1":"PDLI5_HUMAN","accession2":"RPGF2_HUMAN","experiments":1},{"accession1":"PDLI5_HUMAN","accession2":"SLMAP_HUMAN","experiments":1},{"accession1":"PDLI5_HUMAN","accession2":"DAB2P_HUMAN","experiments":1},{"accession1":"PDLI5_HUMAN","accession2":"DMD_HUMAN","experiments":1},{"accession1":"PDLI5_HUMAN","accession2":"SRGP2_HUMAN","experiments":1},{"accession1":"PDLI5_HUMAN","accession2":"SYGP1_HUMAN","experiments":1}]},{"accession":"PRIC2_HUMAN","name":"PRIC2_HUMAN","interactions":[{"accession1":"PRIC2_HUMAN","accession2":"RHG26_HUMAN","experiments":1},{"accession1":"PRIC2_HUMAN","accession2":"RHG21_HUMAN","experiments":1},{"accession1":"PRIC2_HUMAN","accession2":"NCK2_HUMAN","experiments":1},{"accession1":"PRIC2_HUMAN","accession2":"DOCK1_HUMAN","experiments":1},{"accession1":"PRIC2_HUMAN","accession2":"ARHG2_HUMAN","experiments":1},{"accession1":"PRIC2_HUMAN","accession2":"RPGF4_HUMAN","experiments":1},{"accession1":"PRIC2_HUMAN","accession2":"SOS1_HUMAN","experiments":1},{"accession1":"PRIC2_HUMAN","accession2":"SRBS2_HUMAN","experiments":1},{"accession1":"PRIC2_HUMAN","accession2":"PDLI5_HUMAN","experiments":1},{"accession1":"PRIC2_HUMAN","accession2":"RBP1_HUMAN","experiments":1},{"accession1":"PRIC2_HUMAN","accession2":"FGD4_HUMAN","experiments":1},{"accession1":"PRIC2_HUMAN","accession2":"SRBS1_HUMAN","experiments":1},{"accession1":"PRIC2_HUMAN","accession2":"SLMAP_HUMAN","experiments":1},{"accession1":"PRIC2_HUMAN","accession2":"EPS8_HUMAN","experiments":1},{"accession1":"PRIC2_HUMAN","accession2":"DAB2P_HUMAN","experiments":1},{"accession1":"PRIC2_HUMAN","accession2":"SC6A4_HUMAN","experiments":1},{"accession1":"PRIC2_HUMAN","accession2":"DMD_HUMAN","experiments":1},{"accession1":"PRIC2_HUMAN","accession2":"SRGP2_HUMAN","experiments":1},{"accession1":"PRIC2_HUMAN","accession2":"SYGP1_HUMAN","experiments":1}]},{"accession":"FAK1_HUMAN","name":"FAK1_HUMAN","interactions":[{"accession1":"FAK1_HUMAN","accession2":"RHG26_HUMAN","experiments":2},{"accession1":"FAK1_HUMAN","accession2":"CDC42_HUMAN","experiments":1},{"accession1":"FAK1_HUMAN","accession2":"NCK2_HUMAN","experiments":3},{"accession1":"FAK1_HUMAN","accession2":"DOCK1_HUMAN","experiments":1},{"accession1":"FAK1_HUMAN","accession2":"ARHG2_HUMAN","experiments":1},{"accession1":"FAK1_HUMAN","accession2":"SOS1_HUMAN","experiments":1},{"accession1":"FAK1_HUMAN","accession2":"FAK1_HUMAN","experiments":10},{"accession1":"FAK1_HUMAN","accession2":"PTEN_HUMAN","experiments":9},{"accession1":"FAK1_HUMAN","accession2":"SRBS1_HUMAN","experiments":2},{"accession1":"FAK1_HUMAN","accession2":"RHOA_HUMAN","experiments":1},{"accession1":"FAK1_HUMAN","accession2":"DMD_HUMAN","experiments":1}]},{"accession":"PTEN_HUMAN","name":"PTEN_HUMAN","interactions":[{"accession1":"PTEN_HUMAN","accession2":"RHG26_HUMAN","experiments":1},{"accession1":"PTEN_HUMAN","accession2":"CDC42_HUMAN","experiments":1},{"accession1":"PTEN_HUMAN","accession2":"FAK1_HUMAN","experiments":9},{"accession1":"PTEN_HUMAN","accession2":"PTEN_HUMAN","experiments":10},{"accession1":"PTEN_HUMAN","accession2":"RHOA_HUMAN","experiments":3}]},{"accession":"CAH2_HUMAN","name":"CAH2_HUMAN","interactions":[{"accession1":"CAH2_HUMAN","accession2":"RHG26_HUMAN","experiments":2},{"accession1":"CAH2_HUMAN","accession2":"KC1E_HUMAN","experiments":1},{"accession1":"CAH2_HUMAN","accession2":"CAH2_HUMAN","experiments":10}]},{"accession":"RBP1_HUMAN","name":"RBP1_HUMAN","interactions":[{"accession1":"RBP1_HUMAN","accession2":"RHG26_HUMAN","experiments":1},{"accession1":"RBP1_HUMAN","accession2":"CDC42_HUMAN","experiments":1},{"accession1":"RBP1_HUMAN","accession2":"RHG21_HUMAN","experiments":1},{"accession1":"RBP1_HUMAN","accession2":"DOCK1_HUMAN","experiments":1},{"accession1":"RBP1_HUMAN","accession2":"PDLI5_HUMAN","experiments":2},{"accession1":"RBP1_HUMAN","accession2":"PRIC2_HUMAN","experiments":1},{"accession1":"RBP1_HUMAN","accession2":"RBP1_HUMAN","experiments":2},{"accession1":"RBP1_HUMAN","accession2":"FGD4_HUMAN","experiments":1},{"accession1":"RBP1_HUMAN","accession2":"SLMAP_HUMAN","experiments":1},{"accession1":"RBP1_HUMAN","accession2":"OPHN1_HUMAN","experiments":1},{"accession1":"RBP1_HUMAN","accession2":"RHOA_HUMAN","experiments":1},{"accession1":"RBP1_HUMAN","accession2":"SRGP2_HUMAN","experiments":1},{"accession1":"RBP1_HUMAN","accession2":"SYGP1_HUMAN","experiments":1}]},{"accession":"FGD4_HUMAN","name":"FGD4_HUMAN","interactions":[{"accession1":"FGD4_HUMAN","accession2":"RHG26_HUMAN","experiments":1},{"accession1":"FGD4_HUMAN","accession2":"CDC42_HUMAN","experiments":1},{"accession1":"FGD4_HUMAN","accession2":"RHG21_HUMAN","experiments":1},{"accession1":"FGD4_HUMAN","accession2":"DOCK1_HUMAN","experiments":1},{"accession1":"FGD4_HUMAN","accession2":"ARHG2_HUMAN","experiments":1},{"accession1":"FGD4_HUMAN","accession2":"PDLI5_HUMAN","experiments":1},{"accession1":"FGD4_HUMAN","accession2":"PRIC2_HUMAN","experiments":1},{"accession1":"FGD4_HUMAN","accession2":"RBP1_HUMAN","experiments":1},{"accession1":"FGD4_HUMAN","accession2":"SRBS1_HUMAN","experiments":1},{"accession1":"FGD4_HUMAN","accession2":"SLMAP_HUMAN","experiments":1},{"accession1":"FGD4_HUMAN","accession2":"DAB2P_HUMAN","experiments":1},{"accession1":"FGD4_HUMAN","accession2":"SRGP2_HUMAN","experiments":1},{"accession1":"FGD4_HUMAN","accession2":"SYGP1_HUMAN","experiments":1}]},{"accession":"SRBS1_HUMAN","name":"SRBS1_HUMAN","interactions":[{"accession1":"SRBS1_HUMAN","accession2":"RHG26_HUMAN","experiments":1},{"accession1":"SRBS1_HUMAN","accession2":"RHG21_HUMAN","experiments":1},{"accession1":"SRBS1_HUMAN","accession2":"NCK2_HUMAN","experiments":2},{"accession1":"SRBS1_HUMAN","accession2":"ARHG2_HUMAN","experiments":1},{"accession1":"SRBS1_HUMAN","accession2":"SOS1_HUMAN","experiments":1},{"accession1":"SRBS1_HUMAN","accession2":"SRBS2_HUMAN","experiments":1},{"accession1":"SRBS1_HUMAN","accession2":"PDLI5_HUMAN","experiments":1},{"accession1":"SRBS1_HUMAN","accession2":"PRIC2_HUMAN","experiments":1},{"accession1":"SRBS1_HUMAN","accession2":"FAK1_HUMAN","experiments":2},{"accession1":"SRBS1_HUMAN","accession2":"FGD4_HUMAN","experiments":1},{"accession1":"SRBS1_HUMAN","accession2":"EPS8_HUMAN","experiments":1},{"accession1":"SRBS1_HUMAN","accession2":"SC6A4_HUMAN","experiments":1},{"accession1":"SRBS1_HUMAN","accession2":"SRGP2_HUMAN","experiments":1},{"accession1":"SRBS1_HUMAN","accession2":"SYGP1_HUMAN","experiments":1}]},{"accession":"RPGF2_HUMAN","name":"RPGF2_HUMAN","interactions":[{"accession1":"RPGF2_HUMAN","accession2":"RHG26_HUMAN","experiments":1},{"accession1":"RPGF2_HUMAN","accession2":"RPGF4_HUMAN","experiments":1},{"accession1":"RPGF2_HUMAN","accession2":"SOS1_HUMAN","experiments":1},{"accession1":"RPGF2_HUMAN","accession2":"PDLI5_HUMAN","experiments":1},{"accession1":"RPGF2_HUMAN","accession2":"OPHN1_HUMAN","experiments":1},{"accession1":"RPGF2_HUMAN","accession2":"DAB2P_HUMAN","experiments":1},{"accession1":"RPGF2_HUMAN","accession2":"SC6A4_HUMAN","experiments":1},{"accession1":"RPGF2_HUMAN","accession2":"SYGP1_HUMAN","experiments":1}]},{"accession":"SLMAP_HUMAN","name":"SLMAP_HUMAN","interactions":[{"accession1":"SLMAP_HUMAN","accession2":"RHG26_HUMAN","experiments":1},{"accession1":"SLMAP_HUMAN","accession2":"RHG21_HUMAN","experiments":1},{"accession1":"SLMAP_HUMAN","accession2":"PDLI5_HUMAN","experiments":1},{"accession1":"SLMAP_HUMAN","accession2":"PRIC2_HUMAN","experiments":1},{"accession1":"SLMAP_HUMAN","accession2":"RBP1_HUMAN","experiments":1},{"accession1":"SLMAP_HUMAN","accession2":"FGD4_HUMAN","experiments":1},{"accession1":"SLMAP_HUMAN","accession2":"OPHN1_HUMAN","experiments":1},{"accession1":"SLMAP_HUMAN","accession2":"RHOA_HUMAN","experiments":1},{"accession1":"SLMAP_HUMAN","accession2":"SRGP2_HUMAN","experiments":1},{"accession1":"SLMAP_HUMAN","accession2":"SYGP1_HUMAN","experiments":1}]},{"accession":"OPHN1_HUMAN","name":"OPHN1_HUMAN","interactions":[{"accession1":"OPHN1_HUMAN","accession2":"RHG26_HUMAN","experiments":2},{"accession1":"OPHN1_HUMAN","accession2":"CDC42_HUMAN","experiments":2},{"accession1":"OPHN1_HUMAN","accession2":"SRBS2_HUMAN","experiments":1},{"accession1":"OPHN1_HUMAN","accession2":"RBP1_HUMAN","experiments":1},{"accession1":"OPHN1_HUMAN","accession2":"RPGF2_HUMAN","experiments":1},{"accession1":"OPHN1_HUMAN","accession2":"SLMAP_HUMAN","experiments":1},{"accession1":"OPHN1_HUMAN","accession2":"DAB2P_HUMAN","experiments":1},{"accession1":"OPHN1_HUMAN","accession2":"RHOA_HUMAN","experiments":2}]},{"accession":"EPS8_HUMAN","name":"EPS8_HUMAN","interactions":[{"accession1":"EPS8_HUMAN","accession2":"RHG26_HUMAN","experiments":1},{"accession1":"EPS8_HUMAN","accession2":"CDC42_HUMAN","experiments":1},{"accession1":"EPS8_HUMAN","accession2":"RHG21_HUMAN","experiments":1},{"accession1":"EPS8_HUMAN","accession2":"ARHG2_HUMAN","experiments":1},{"accession1":"EPS8_HUMAN","accession2":"SOS1_HUMAN","experiments":5},{"accession1":"EPS8_HUMAN","accession2":"SRBS2_HUMAN","experiments":1},{"accession1":"EPS8_HUMAN","accession2":"PRIC2_HUMAN","experiments":1},{"accession1":"EPS8_HUMAN","accession2":"SRBS1_HUMAN","experiments":1},{"accession1":"EPS8_HUMAN","accession2":"EPS8_HUMAN","experiments":10}]},{"accession":"DAB2P_HUMAN","name":"DAB2P_HUMAN","interactions":[{"accession1":"DAB2P_HUMAN","accession2":"RHG26_HUMAN","experiments":1},{"accession1":"DAB2P_HUMAN","accession2":"RHG21_HUMAN","experiments":1},{"accession1":"DAB2P_HUMAN","accession2":"ARHG2_HUMAN","experiments":1},{"accession1":"DAB2P_HUMAN","accession2":"SOS1_HUMAN","experiments":1},{"accession1":"DAB2P_HUMAN","accession2":"PDLI5_HUMAN","experiments":1},{"accession1":"DAB2P_HUMAN","accession2":"PRIC2_HUMAN","experiments":1},{"accession1":"DAB2P_HUMAN","accession2":"FGD4_HUMAN","experiments":1},{"accession1":"DAB2P_HUMAN","accession2":"RPGF2_HUMAN","experiments":1},{"accession1":"DAB2P_HUMAN","accession2":"OPHN1_HUMAN","experiments":1},{"accession1":"DAB2P_HUMAN","accession2":"DAB2P_HUMAN","experiments":4},{"accession1":"DAB2P_HUMAN","accession2":"SC6A4_HUMAN","experiments":1},{"accession1":"DAB2P_HUMAN","accession2":"ANS1B_HUMAN","experiments":1},{"accession1":"DAB2P_HUMAN","accession2":"SYGP1_HUMAN","experiments":1}]},{"accession":"SC6A4_HUMAN","name":"SC6A4_HUMAN","interactions":[{"accession1":"SC6A4_HUMAN","accession2":"RHG26_HUMAN","experiments":1},{"accession1":"SC6A4_HUMAN","accession2":"CDC42_HUMAN","experiments":1},{"accession1":"SC6A4_HUMAN","accession2":"KC1E_HUMAN","experiments":1},{"accession1":"SC6A4_HUMAN","accession2":"RHG21_HUMAN","experiments":1},{"accession1":"SC6A4_HUMAN","accession2":"MARE2_HUMAN","experiments":1},{"accession1":"SC6A4_HUMAN","accession2":"SRBS2_HUMAN","experiments":1},{"accession1":"SC6A4_HUMAN","accession2":"PRIC2_HUMAN","experiments":1},{"accession1":"SC6A4_HUMAN","accession2":"SRBS1_HUMAN","experiments":1},{"accession1":"SC6A4_HUMAN","accession2":"RPGF2_HUMAN","experiments":1},{"accession1":"SC6A4_HUMAN","accession2":"DAB2P_HUMAN","experiments":1},{"accession1":"SC6A4_HUMAN","accession2":"SC6A4_HUMAN","experiments":1},{"accession1":"SC6A4_HUMAN","accession2":"ANS1B_HUMAN","experiments":1},{"accession1":"SC6A4_HUMAN","accession2":"KC1D_HUMAN","experiments":1}]},{"accession":"RFIP5_HUMAN","name":"RFIP5_HUMAN","interactions":[{"accession1":"RFIP5_HUMAN","accession2":"RHG26_HUMAN","experiments":2},{"accession1":"RFIP5_HUMAN","accession2":"CDC42_HUMAN","experiments":1},{"accession1":"RFIP5_HUMAN","accession2":"GCR_HUMAN","experiments":1},{"accession1":"RFIP5_HUMAN","accession2":"RFIP5_HUMAN","experiments":2}]},{"accession":"RHOA_HUMAN","name":"RHOA_HUMAN","interactions":[{"accession1":"RHOA_HUMAN","accession2":"RHG26_HUMAN","experiments":2},{"accession1":"RHOA_HUMAN","accession2":"CDC42_HUMAN","experiments":2},{"accession1":"RHOA_HUMAN","accession2":"RHG21_HUMAN","experiments":2},{"accession1":"RHOA_HUMAN","accession2":"DOCK1_HUMAN","experiments":1},{"accession1":"RHOA_HUMAN","accession2":"ARHG2_HUMAN","experiments":10},{"accession1":"RHOA_HUMAN","accession2":"GCR_HUMAN","experiments":1},{"accession1":"RHOA_HUMAN","accession2":"FAK1_HUMAN","experiments":1},{"accession1":"RHOA_HUMAN","accession2":"PTEN_HUMAN","experiments":3},{"accession1":"RHOA_HUMAN","accession2":"RBP1_HUMAN","experiments":1},{"accession1":"RHOA_HUMAN","accession2":"SLMAP_HUMAN","experiments":1},{"accession1":"RHOA_HUMAN","accession2":"OPHN1_HUMAN","experiments":2},{"accession1":"RHOA_HUMAN","accession2":"RHOA_HUMAN","experiments":10},{"accession1":"RHOA_HUMAN","accession2":"ANS1B_HUMAN","experiments":1}]},{"accession":"ANS1B_HUMAN","name":"ANS1B_HUMAN","interactions":[{"accession1":"ANS1B_HUMAN","accession2":"RHG26_HUMAN","experiments":1},{"accession1":"ANS1B_HUMAN","accession2":"NCK2_HUMAN","experiments":1},{"accession1":"ANS1B_HUMAN","accession2":"MARE2_HUMAN","experiments":1},{"accession1":"ANS1B_HUMAN","accession2":"DAB2P_HUMAN","experiments":1},{"accession1":"ANS1B_HUMAN","accession2":"SC6A4_HUMAN","experiments":1},{"accession1":"ANS1B_HUMAN","accession2":"RHOA_HUMAN","experiments":1},{"accession1":"ANS1B_HUMAN","accession2":"SRGP2_HUMAN","experiments":1},{"accession1":"ANS1B_HUMAN","accession2":"SYGP1_HUMAN","experiments":4}]},{"accession":"DMD_HUMAN","name":"DMD_HUMAN","interactions":[{"accession1":"DMD_HUMAN","accession2":"RHG26_HUMAN","experiments":1},{"accession1":"DMD_HUMAN","accession2":"DOCK1_HUMAN","experiments":1},{"accession1":"DMD_HUMAN","accession2":"SOS1_HUMAN","experiments":1},{"accession1":"DMD_HUMAN","accession2":"PDLI5_HUMAN","experiments":1},{"accession1":"DMD_HUMAN","accession2":"PRIC2_HUMAN","experiments":1},{"accession1":"DMD_HUMAN","accession2":"FAK1_HUMAN","experiments":1},{"accession1":"DMD_HUMAN","accession2":"DMD_HUMAN","experiments":8}]},{"accession":"SRGP2_HUMAN","name":"SRGP2_HUMAN","interactions":[{"accession1":"SRGP2_HUMAN","accession2":"RHG26_HUMAN","experiments":1},{"accession1":"SRGP2_HUMAN","accession2":"CDC42_HUMAN","experiments":1},{"accession1":"SRGP2_HUMAN","accession2":"RHG21_HUMAN","experiments":1},{"accession1":"SRGP2_HUMAN","accession2":"DOCK1_HUMAN","experiments":1},{"accession1":"SRGP2_HUMAN","accession2":"RPGF4_HUMAN","experiments":1},{"accession1":"SRGP2_HUMAN","accession2":"SRBS2_HUMAN","experiments":1},{"accession1":"SRGP2_HUMAN","accession2":"PDLI5_HUMAN","experiments":1},{"accession1":"SRGP2_HUMAN","accession2":"PRIC2_HUMAN","experiments":1},{"accession1":"SRGP2_HUMAN","accession2":"RBP1_HUMAN","experiments":1},{"accession1":"SRGP2_HUMAN","accession2":"FGD4_HUMAN","experiments":1},{"accession1":"SRGP2_HUMAN","accession2":"SRBS1_HUMAN","experiments":1},{"accession1":"SRGP2_HUMAN","accession2":"SLMAP_HUMAN","experiments":1},{"accession1":"SRGP2_HUMAN","accession2":"ANS1B_HUMAN","experiments":1},{"accession1":"SRGP2_HUMAN","accession2":"SRGP2_HUMAN","experiments":10},{"accession1":"SRGP2_HUMAN","accession2":"SYGP1_HUMAN","experiments":2}]},{"accession":"SYGP1_HUMAN","name":"SYGP1_HUMAN","interactions":[{"accession1":"SYGP1_HUMAN","accession2":"RHG26_HUMAN","experiments":1},{"accession1":"SYGP1_HUMAN","accession2":"RHG21_HUMAN","experiments":1},{"accession1":"SYGP1_HUMAN","accession2":"NCK2_HUMAN","experiments":4},{"accession1":"SYGP1_HUMAN","accession2":"DOCK1_HUMAN","experiments":1},{"accession1":"SYGP1_HUMAN","accession2":"ARHG2_HUMAN","experiments":1},{"accession1":"SYGP1_HUMAN","accession2":"SRBS2_HUMAN","experiments":1},{"accession1":"SYGP1_HUMAN","accession2":"PDLI5_HUMAN","experiments":1},{"accession1":"SYGP1_HUMAN","accession2":"PRIC2_HUMAN","experiments":1},{"accession1":"SYGP1_HUMAN","accession2":"RBP1_HUMAN","experiments":1},{"accession1":"SYGP1_HUMAN","accession2":"FGD4_HUMAN","experiments":1},{"accession1":"SYGP1_HUMAN","accession2":"SRBS1_HUMAN","experiments":1},{"accession1":"SYGP1_HUMAN","accession2":"RPGF2_HUMAN","experiments":1},{"accession1":"SYGP1_HUMAN","accession2":"SLMAP_HUMAN","experiments":1},{"accession1":"SYGP1_HUMAN","accession2":"DAB2P_HUMAN","experiments":1},{"accession1":"SYGP1_HUMAN","accession2":"ANS1B_HUMAN","experiments":4},{"accession1":"SYGP1_HUMAN","accession2":"SRGP2_HUMAN","experiments":2},{"accession1":"SYGP1_HUMAN","accession2":"SYGP1_HUMAN","experiments":5}]},{"accession":"KC1D_HUMAN","name":"KC1D_HUMAN","interactions":[{"accession1":"KC1D_HUMAN","accession2":"RHG26_HUMAN","experiments":2},{"accession1":"KC1D_HUMAN","accession2":"KC1E_HUMAN","experiments":6},{"accession1":"KC1D_HUMAN","accession2":"RHG21_HUMAN","experiments":1},{"accession1":"KC1D_HUMAN","accession2":"SC6A4_HUMAN","experiments":1},{"accession1":"KC1D_HUMAN","accession2":"KC1D_HUMAN","experiments":10}]}]