[{"accession":"SYT4_HUMAN","name":"SYT4_HUMAN","interactions":[{"accession1":"SYT4_HUMAN","accession2":"STX1A_HUMAN","experiments":1},{"accession1":"SYT4_HUMAN","accession2":"PRKN_HUMAN","experiments":4},{"accession1":"SYT4_HUMAN","accession2":"STX3_HUMAN","experiments":1},{"accession1":"SYT4_HUMAN","accession2":"MK10_HUMAN","experiments":2},{"accession1":"SYT4_HUMAN","accession2":"NDUAC_HUMAN","experiments":3},{"accession1":"SYT4_HUMAN","accession2":"SYT1_HUMAN","experiments":2},{"accession1":"SYT4_HUMAN","accession2":"CPLX1_HUMAN","experiments":1},{"accession1":"SYT4_HUMAN","accession2":"HNRPQ_HUMAN","experiments":1},{"accession1":"SYT4_HUMAN","accession2":"SNP25_HUMAN","experiments":1},{"accession1":"SYT4_HUMAN","accession2":"SYT4_HUMAN","experiments":6},{"accession1":"SYT4_HUMAN","accession2":"STX1B_HUMAN","experiments":1}]},{"accession":"STX1A_HUMAN","name":"STX1A_HUMAN","interactions":[{"accession1":"STX1A_HUMAN","accession2":"SYT4_HUMAN","experiments":1},{"accession1":"STX1A_HUMAN","accession2":"STX1A_HUMAN","experiments":10},{"accession1":"STX1A_HUMAN","accession2":"STX3_HUMAN","experiments":3},{"accession1":"STX1A_HUMAN","accession2":"SYT1_HUMAN","experiments":10},{"accession1":"STX1A_HUMAN","accession2":"CPLX1_HUMAN","experiments":10},{"accession1":"STX1A_HUMAN","accession2":"SNP25_HUMAN","experiments":10},{"accession1":"STX1A_HUMAN","accession2":"SYT4_HUMAN","experiments":1},{"accession1":"STX1A_HUMAN","accession2":"STX1B_HUMAN","experiments":1}]},{"accession":"PRKN_HUMAN","name":"PRKN_HUMAN","interactions":[{"accession1":"PRKN_HUMAN","accession2":"SYT4_HUMAN","experiments":4},{"accession1":"PRKN_HUMAN","accession2":"PRKN_HUMAN","experiments":10},{"accession1":"PRKN_HUMAN","accession2":"HNRPQ_HUMAN","experiments":1},{"accession1":"PRKN_HUMAN","accession2":"SYT4_HUMAN","experiments":4}]},{"accession":"STX3_HUMAN","name":"STX3_HUMAN","interactions":[{"accession1":"STX3_HUMAN","accession2":"SYT4_HUMAN","experiments":1},{"accession1":"STX3_HUMAN","accession2":"STX1A_HUMAN","experiments":3},{"accession1":"STX3_HUMAN","accession2":"SYT1_HUMAN","experiments":2},{"accession1":"STX3_HUMAN","accession2":"CPLX1_HUMAN","experiments":1},{"accession1":"STX3_HUMAN","accession2":"SNP25_HUMAN","experiments":8},{"accession1":"STX3_HUMAN","accession2":"SYT4_HUMAN","experiments":1}]},{"accession":"MK10_HUMAN","name":"MK10_HUMAN","interactions":[{"accession1":"MK10_HUMAN","accession2":"SYT4_HUMAN","experiments":2},{"accession1":"MK10_HUMAN","accession2":"MK10_HUMAN","experiments":10},{"accession1":"MK10_HUMAN","accession2":"SYT4_HUMAN","experiments":2}]},{"accession":"NDUAC_HUMAN","name":"NDUAC_HUMAN","interactions":[{"accession1":"NDUAC_HUMAN","accession2":"SYT4_HUMAN","experiments":3},{"accession1":"NDUAC_HUMAN","accession2":"SYT4_HUMAN","experiments":3}]},{"accession":"SYT1_HUMAN","name":"SYT1_HUMAN","interactions":[{"accession1":"SYT1_HUMAN","accession2":"SYT4_HUMAN","experiments":2},{"accession1":"SYT1_HUMAN","accession2":"STX1A_HUMAN","experiments":10},{"accession1":"SYT1_HUMAN","accession2":"STX3_HUMAN","experiments":2},{"accession1":"SYT1_HUMAN","accession2":"SYT1_HUMAN","experiments":10},{"accession1":"SYT1_HUMAN","accession2":"CPLX1_HUMAN","experiments":4},{"accession1":"SYT1_HUMAN","accession2":"HNRPQ_HUMAN","experiments":1},{"accession1":"SYT1_HUMAN","accession2":"SNP25_HUMAN","experiments":10},{"accession1":"SYT1_HUMAN","accession2":"SYT4_HUMAN","experiments":2},{"accession1":"SYT1_HUMAN","accession2":"STX1B_HUMAN","experiments":1}]},{"accession":"CPLX1_HUMAN","name":"CPLX1_HUMAN","interactions":[{"accession1":"CPLX1_HUMAN","accession2":"SYT4_HUMAN","experiments":1},{"accession1":"CPLX1_HUMAN","accession2":"STX1A_HUMAN","experiments":10},{"accession1":"CPLX1_HUMAN","accession2":"STX3_HUMAN","experiments":1},{"accession1":"CPLX1_HUMAN","accession2":"SYT1_HUMAN","experiments":4},{"accession1":"CPLX1_HUMAN","accession2":"CPLX1_HUMAN","experiments":6},{"accession1":"CPLX1_HUMAN","accession2":"SNP25_HUMAN","experiments":8},{"accession1":"CPLX1_HUMAN","accession2":"SYT4_HUMAN","experiments":1},{"accession1":"CPLX1_HUMAN","accession2":"STX1B_HUMAN","experiments":1}]},{"accession":"HNRPQ_HUMAN","name":"HNRPQ_HUMAN","interactions":[{"accession1":"HNRPQ_HUMAN","accession2":"SYT4_HUMAN","experiments":1},{"accession1":"HNRPQ_HUMAN","accession2":"PRKN_HUMAN","experiments":1},{"accession1":"HNRPQ_HUMAN","accession2":"SYT1_HUMAN","experiments":1},{"accession1":"HNRPQ_HUMAN","accession2":"SYT4_HUMAN","experiments":1}]},{"accession":"SNP25_HUMAN","name":"SNP25_HUMAN","interactions":[{"accession1":"SNP25_HUMAN","accession2":"SYT4_HUMAN","experiments":1},{"accession1":"SNP25_HUMAN","accession2":"STX1A_HUMAN","experiments":10},{"accession1":"SNP25_HUMAN","accession2":"STX3_HUMAN","experiments":8},{"accession1":"SNP25_HUMAN","accession2":"SYT1_HUMAN","experiments":10},{"accession1":"SNP25_HUMAN","accession2":"CPLX1_HUMAN","experiments":8},{"accession1":"SNP25_HUMAN","accession2":"SNP25_HUMAN","experiments":10},{"accession1":"SNP25_HUMAN","accession2":"SYT4_HUMAN","experiments":1},{"accession1":"SNP25_HUMAN","accession2":"STX1B_HUMAN","experiments":2}]},{"accession":"SYT4_HUMAN","name":"SYT4_HUMAN","interactions":[{"accession1":"SYT4_HUMAN","accession2":"SYT4_HUMAN","experiments":6},{"accession1":"SYT4_HUMAN","accession2":"STX1A_HUMAN","experiments":1},{"accession1":"SYT4_HUMAN","accession2":"PRKN_HUMAN","experiments":4},{"accession1":"SYT4_HUMAN","accession2":"STX3_HUMAN","experiments":1},{"accession1":"SYT4_HUMAN","accession2":"MK10_HUMAN","experiments":2},{"accession1":"SYT4_HUMAN","accession2":"NDUAC_HUMAN","experiments":3},{"accession1":"SYT4_HUMAN","accession2":"SYT1_HUMAN","experiments":2},{"accession1":"SYT4_HUMAN","accession2":"CPLX1_HUMAN","experiments":1},{"accession1":"SYT4_HUMAN","accession2":"HNRPQ_HUMAN","experiments":1},{"accession1":"SYT4_HUMAN","accession2":"SNP25_HUMAN","experiments":1},{"accession1":"SYT4_HUMAN","accession2":"SYT4_HUMAN","experiments":6},{"accession1":"SYT4_HUMAN","accession2":"STX1B_HUMAN","experiments":1}]},{"accession":"STX1B_HUMAN","name":"STX1B_HUMAN","interactions":[{"accession1":"STX1B_HUMAN","accession2":"SYT4_HUMAN","experiments":1},{"accession1":"STX1B_HUMAN","accession2":"STX1A_HUMAN","experiments":1},{"accession1":"STX1B_HUMAN","accession2":"SYT1_HUMAN","experiments":1},{"accession1":"STX1B_HUMAN","accession2":"CPLX1_HUMAN","experiments":1},{"accession1":"STX1B_HUMAN","accession2":"SNP25_HUMAN","experiments":2},{"accession1":"STX1B_HUMAN","accession2":"SYT4_HUMAN","experiments":1}]}]